LICENSE.txt
MANIFEST.in
README.rst
setup.py
hal_impl/__init__.py
hal_impl/data.py
hal_impl/fndef.py
hal_impl/functions.py
hal_impl/i2c_helpers.py
hal_impl/mode_helpers.py
hal_impl/sim_hooks.py
hal_impl/spi_helpers.py
hal_impl/types.py
hal_impl/version.py
robotpy_hal_sim.egg-info/PKG-INFO
robotpy_hal_sim.egg-info/SOURCES.txt
robotpy_hal_sim.egg-info/dependency_links.txt
robotpy_hal_sim.egg-info/requires.txt
robotpy_hal_sim.egg-info/top_level.txt