Metadata-Version: 1.1
Name: robotpy-hal-sim
Version: 2017.0.4
Summary: WPILib HAL layer for simulations
Home-page: https://github.com/robotpy/robotpy-wpilib
Author: Peter Johnson, Dustin Spicuzza
Author-email: robotpy@googlegroups.com
License: BSD License
Keywords: frc first robotics hal can
Platform: UNKNOWN
Classifier: Development Status :: 5 - Production/Stable
Classifier: Intended Audience :: Developers
Classifier: Intended Audience :: Education
Classifier: License :: OSI Approved :: BSD License
Classifier: Operating System :: OS Independent
Classifier: Programming Language :: Python :: 3.4
Classifier: Programming Language :: Python :: 3.5
Classifier: Topic :: Scientific/Engineering
